pyredactkit/__init__.py
pyredactkit/__main__.py
pyredactkit/common_jobs.py
pyredactkit/core_redactor.py
pyredactkit/custom_redactor.py
pyredactkit/identifiers.py
pyredactkit/pyredactkit.py
pyredactkit/unredact.py
pyredactkit-0.3.3.dist-info/entry_points.txt
pyredactkit-0.3.3.dist-info/LICENSE
pyredactkit-0.3.3.dist-info/WHEEL
pyredactkit-0.3.3.dist-info/METADATA
pyredactkit-0.3.3.dist-info/RECORD
