Metadata-Version: 2.1
Name: pyredactkit
Version: 0.3.3
Summary: Python cli tool to redact sensitive data
Home-page: https://github.com/brootware/PyRedactKit
License: GPL-3.0-or-later
Author: brootware
Author-email: brootware@outlook.com
Requires-Python: >=3.7,<4.0
Classifier: Development Status :: 5 - Production/Stable
Classifier: Intended Audience :: Information Technology
Classifier: License :: OSI Approved :: GNU General Public License v3 or later (GPLv3+)
Classifier: Operating System :: OS Independent
Classifier: Programming Language :: Python :: 3
Classifier: Programming Language :: Python :: 3.10
Classifier: Programming Language :: Python :: 3.7
Classifier: Programming Language :: Python :: 3.8
Classifier: Programming Language :: Python :: 3.9
Classifier: Topic :: Internet :: Log Analysis
Classifier: Topic :: Security
Classifier: Topic :: Text Processing :: General
Requires-Dist: nltk (>=3.7,<4.0)
Requires-Dist: numpy (<1.22.0)
Project-URL: Repository, https://github.com/brootware/PyRedactKit
